haxmas_day_9_jojocoding/__init__.py
haxmas_day_9_jojocoding/main.py
haxmas_day_9_jojocoding-0.1.0.dist-info/METADATA
haxmas_day_9_jojocoding-0.1.0.dist-info/WHEEL
haxmas_day_9_jojocoding-0.1.0.dist-info/entry_points.txt
haxmas_day_9_jojocoding-0.1.0.dist-info/licenses/LICENSE
haxmas_day_9_jojocoding-0.1.0.dist-info/RECORD
