Metadata-Version: 2.4
Name: haxmas_day_9_jojocoding
Version: 0.1.0
Summary: Add your description here
License-File: LICENSE
Requires-Python: >=3.13
Requires-Dist: textual-dev>=1.8.0
